Buoy_Client-0.0.2-py3.6-nspkg.pth
buoy/client/__init__.py
buoy/client/current_meter.py
buoy/client/internet_connection.py
buoy/client/reboot_computer.py
buoy/client/weather_station.py
buoy/client/zte.py
buoy/client/device/__init__.py
buoy/client/device/common/__init__.py
buoy/client/device/common/base.py
buoy/client/device/common/database.py
buoy/client/device/common/exceptions.py
buoy/client/device/common/item.py
buoy/client/device/common/nmea0183.py
buoy/client/device/currentmeter/__init__.py
buoy/client/device/currentmeter/acmplus.py
buoy/client/device/currentmeter/item.py
buoy/client/device/weatherstation/__init__.py
buoy/client/device/weatherstation/pb200.py
buoy/client/network/__init__.py
buoy/client/network/connection.py
buoy/client/network/ip.py
buoy/client/notification/__init__.py
buoy/client/notification/common.py
buoy/client/notification/exceptions.py
buoy/client/notification/client/__init__.py
buoy/client/notification/client/common.py
buoy/client/service/__init__.py
buoy/client/service/daemon.py
buoy/client/utils/__init__.py
buoy/client/utils/argsparse.py
buoy/client/utils/config.py
etc/buoy/buoy.yaml
etc/buoy/ip.yaml
etc/buoy/logging.yaml
test/__init__.py
test/test_commands_line.py
test/client/__init__.py
test/client/device/__init__.py
test/client/device/common/__init__.py
test/client/device/common/test_data_encoder.py
test/client/device/common/test_device.py
test/client/device/common/test_device_reader_thread.py
test/client/device/common/test_item_save_thread.py
test/client/device/common/test_item_send_thread.py
test/client/device/common/test_thread_base.py
test/client/device/currentmeter/__init__.py
test/client/device/currentmeter/test_acm_plus_item_calculated.py
test/client/device/currentmeter/test_acmplus_parser.py
test/client/device/currentmeter/test_current_meter.py
test/client/device/database/__init__.py
test/client/device/database/test_db_get_items_to_send.py
test/client/device/database/test_db_save.py
Buoy_Client-0.0.2.dist-info/LICENSE
Buoy_Client-0.0.2.dist-info/METADATA
Buoy_Client-0.0.2.dist-info/WHEEL
Buoy_Client-0.0.2.dist-info/entry_points.txt
Buoy_Client-0.0.2.dist-info/namespace_packages.txt
Buoy_Client-0.0.2.dist-info/top_level.txt
Buoy_Client-0.0.2.dist-info/RECORD
